Workbook

Sheet Simulador
B2: Precio del Inmueble | C2: 377500
B3: Inicial % | C3: =C4/C2 -> 0.42384106
B4: Cuota Inicial | C4: 160000
B5: Importe del Prestamo | C5: =C2-C4 -> 217500
B6: TEA | C6: 0.0803
B7: TEM | C7: =(1+C6)^(1/12)-1 -> 0.0064573242
B8: Plazo Meses | C8: 240
B9: Seguro Desgravamen TEM | C9: 0.00028
B10: Seguro Inmueble TNA | C10: 0.0034
B11: Cuota Base | C11: =PMT(C7,C8,-C5) -> 1785.4006
B12: Cuota Mensual Extraordinaria | C12: =C11 + (C5*C9) + (C2*C10/12)+C13 -> 1953.259
B13: Aporte Extra Capital

Sheet Amortizacion
A1: Mes | B1: Saldo Inicial | C1: Cuota Base | D1: Interes | E1: Capital | F1: Aporte Extra | G1: Capital Total | H1: Saldo Final
A2: 1 | B2: =Simulador!C5 -> 217500 | C2: =Simulador!C11 -> 1785.4006 | D2: =B2*Simulador!C7 -> 1404.468 | E2: =C2-D2 -> 380.93262 | F2: 2000 | G2: =E2+F2 -> 2380.9326 | H2: =B2-G2 -> 215119.07
A3: 2 | B3: =H2 -> 215119.07 | C3: =Simulador!C11 -> 1785.4006 | D3: =B3*Simulador!C7 -> 1389.0936 | E3: =C3-D3 -> 396.30707 | F3: 2000 | G3: =E3+F3 -> 2396.3071 | H3: =B3-G3 -> 212722.76
A4: 3 | B4: =H3 -> 212722.76 | C4: =Simulador!C11 -> 1785.4006 | D4: =B4*Simulador!C7 -> 1373.6198 | E4: =C4-D4 -> 411.78081 | F4: 2000 | G4: =E4+F4 -> 2411.7808 | H4: =B4-G4 -> 210310.98
A5: 4 | B5: =H4 -> 210310.98 | C5: =Simulador!C11 -> 1785.4006 | D5: =B5*Simulador!C7 -> 1358.0462 | E5: =C5-D5 -> 427.35446 | F5: 2000 | G5: =E5+F5 -> 2427.3545 | H5: =B5-G5 -> 207883.63
A6: 5 | B6: =H5 -> 207883.63 | C6: =Simulador!C11 -> 1785.4006 | D6: =B6*Simulador!C7 -> 1342.372 | E6: =C6-D6 -> 443.02867 | F6: 2000 | G6: =E6+F6 -> 2443.0287 | H6: =B6-G6 -> 205440.6
A7: 6 | B7: =H6 -> 205440.6 | C7: =Simulador!C11 -> 1785.4006 | D7: =B7*Simulador!C7 -> 1326.5965 | E7: =C7-D7 -> 458.8041 | F7: 2000 | G7: =E7+F7 -> 2458.8041 | H7: =B7-G7 -> 202981.79
A8: 7 | B8: =H7 -> 202981.79 | C8: =Simulador!C11 -> 1785.4006 | D8: =B8*Simulador!C7 -> 1310.7192 | E8: =C8-D8 -> 474.6814 | F8: 2000 | G8: =E8+F8 -> 2474.6814 | H8: =B8-G8 -> 200507.11 | K8: =SUM(C2:C79) -> 139261.25
A9: 8 | B9: =H8 -> 200507.11 | C9: =Simulador!C11 -> 1785.4006 | D9: =B9*Simulador!C7 -> 1294.7394 | E9: =C9-D9 -> 490.66122 | F9: 2000 | G9: =E9+F9 -> 2490.6612 | H9: =B9-G9 -> 198016.45 | K9: =SUM(F2:F65) -> 128000 | L9: =SUM(C2:C60) -> 105338.64
A10: 9 | B10: =H9 -> 198016.45 | C10: =Simulador!C11 -> 1785.4006 | D10: =B10*Simulador!C7 -> 1278.6564 | E10: =C10-D10 -> 506.74422 | F10: 2000 | G10: =E10+F10 -> 2506.7442 | H10: =B10-G10 -> 195509.71 | K10: =K8+K9 -> 267261.25
A11: 10 | B11: =H10 -> 195509.71 | C11: =Simulador!C11 -> 1785.4006 | D11: =B11*Simulador!C7 -> 1262.4696 | E11: =C11-D11 -> 522.93108 | F11: 2000 | G11: =E11+F11 -> 2522.9311 | H11: =B11-G11 -> 192986.77
A12: 11 | B12: =H11 -> 192986.77 | C12: =Simulador!C11 -> 1785.4006 | D12: =B12*Simulador!C7 -> 1246.1782 | E12: =C12-D12 -> 539.22247 | F12: 2000 | G12: =E12+F12 -> 2539.2225 | H12: =B12-G12 -> 190447.55
A13: 12 | B13: =H12 -> 190447.55 | C13: =Simulador!C11 -> 1785.4006 | D13: =B13*Simulador!C7 -> 1229.7816 | E13: =C13-D13 -> 555.61905 | F13: 2000 | G13: =E13+F13 -> 2555.619 | H13: =B13-G13 -> 187891.93 | K13: =314/80 -> 3.925
A14: 13 | B14: =H13 -> 187891.93 | C14: =Simulador!C11 -> 1785.4006 | D14: =B14*Simulador!C7 -> 1213.2791 | E14: =C14-D14 -> 572.12151 | F14: 2000 | G14: =E14+F14 -> 2572.1215 | H14: =B14-G14 -> 185319.81
A15: 14 | B15: =H14 -> 185319.81 | C15: =Simulador!C11 -> 1785.4006 | D15: =B15*Simulador!C7 -> 1196.6701 | E15: =C15-D15 -> 588.73053 | F15: 2000 | G15: =E15+F15 -> 2588.7305 | H15: =B15-G15 -> 182731.08
A16: 15 | B16: =H15 -> 182731.08 | C16: =Simulador!C11 -> 1785.4006 | D16: =B16*Simulador!C7 -> 1179.9538 | E16: =C16-D16 -> 605.4468 | F16: 2000 | G16: =E16+F16 -> 2605.4468 | H16: =B16-G16 -> 180125.63
A17: 16 | B17: =H16 -> 180125.63 | C17: =Simulador!C11 -> 1785.4006 | D17: =B17*Simulador!C7 -> 1163.1296 | E17: =C17-D17 -> 622.27102 | F17: 2000 | G17: =E17+F17 -> 2622.271 | H17: =B17-G17 -> 177503.36
A18: 17 | B18: =H17 -> 177503.36 | C18: =Simulador!C11 -> 1785.4006 | D18: =B18*Simulador!C7 -> 1146.1968 | E18: =C18-D18 -> 639.20387 | F18: 2000 | G18: =E18+F18 -> 2639.2039 | H18: =B18-G18 -> 174864.16
A19: 18 | B19: =H18 -> 174864.16 | C19: =Simulador!C11 -> 1785.4006 | D19: =B19*Simulador!C7 -> 1129.1546 | E19: =C19-D19 -> 656.24607 | F19: 2000 | G19: =E19+F19 -> 2656.2461 | H19: =B19-G19 -> 172207.91
A20: 19 | B20: =H19 -> 172207.91 | C20: =Simulador!C11 -> 1785.4006 | D20: =B20*Simulador!C7 -> 1112.0023 | E20: =C20-D20 -> 673.39831 | F20: 2000 | G20: =E20+F20 -> 2673.3983 | H20: =B20-G20 -> 169534.51
A21: 20 | B21: =H20 -> 169534.51 | C21: =Simulador!C11 -> 1785.4006 | D21: =B21*Simulador!C7 -> 1094.7393 | E21: =C21-D21 -> 690.66131 | F21: 2000 | G21: =E21+F21 -> 2690.6613 | H21: =B21-G21 -> 166843.85
A22: 21 | B22: =H21 -> 166843.85 | C22: =Simulador!C11 -> 1785.4006 | D22: =B22*Simulador!C7 -> 1077.3649 | E22: =C22-D22 -> 708.03578 | F22: 2000 | G22: =E22+F22 -> 2708.0358 | H22: =B22-G22 -> 164135.82
A23: 22 | B23: =H22 -> 164135.82 | C23: =Simulador!C11 -> 1785.4006 | D23: =B23*Simulador!C7 -> 1059.8782 | E23: =C23-D23 -> 725.52245 | F23: 2000 | G23: =E23+F23 -> 2725.5224 | H23: =B23-G23 -> 161410.3
A24: 23 | B24: =H23 -> 161410.3 | C24: =Simulador!C11 -> 1785.4006 | D24: =B24*Simulador!C7 -> 1042.2786 | E24: =C24-D24 -> 743.12203 | F24: 2000 | G24: =E24+F24 -> 2743.122 | H24: =B24-G24 -> 158667.17
A25: 24 | B25: =H24 -> 158667.17 | C25: =Simulador!C11 -> 1785.4006 | D25: =B25*Simulador!C7 -> 1024.5654 | E25: =C25-D25 -> 760.83526 | F25: 2000 | G25: =E25+F25 -> 2760.8353 | H25: =B25-G25 -> 155906.34
A26: 25 | B26: =H25 -> 155906.34 | C26: =Simulador!C11 -> 1785.4006 | D26: =B26*Simulador!C7 -> 1006.7378 | E26: =C26-D26 -> 778.66287 | F26: 2000 | G26: =E26+F26 -> 2778.6629 | H26: =B26-G26 -> 153127.68
A27: 26 | B27: =H26 -> 153127.68 | C27: =Simulador!C11 -> 1785.4006 | D27: =B27*Simulador!C7 -> 988.79505 | E27: =C27-D27 -> 796.60559 | F27: 2000 | G27: =E27+F27 -> 2796.6056 | H27: =B27-G27 -> 150331.07
A28: 27 | B28: =H27 -> 150331.07 | C28: =Simulador!C11 -> 1785.4006 | D28: =B28*Simulador!C7 -> 970.73646 | E28: =C28-D28 -> 814.66418 | F28: 2000 | G28: =E28+F28 -> 2814.6642 | H28: =B28-G28 -> 147516.41
A29: 28 | B29: =H28 -> 147516.41 | C29: =Simulador!C11 -> 1785.4006 | D29: =B29*Simulador!C7 -> 952.56126 | E29: =C29-D29 -> 832.83938 | F29: 2000 | G29: =E29+F29 -> 2832.8394 | H29: =B29-G29 -> 144683.57
A30: 29 | B30: =H29 -> 144683.57 | C30: =Simulador!C11 -> 1785.4006 | D30: =B30*Simulador!C7 -> 934.2687 | E30: =C30-D30 -> 851.13194 | F30: 2000 | G30: =E30+F30 -> 2851.1319 | H30: =B30-G30 -> 141832.43
A31: 30 | B31: =H30 -> 141832.43 | C31: =Simulador!C11 -> 1785.4006 | D31: =B31*Simulador!C7 -> 915.85801 | E31: =C31-D31 -> 869.54263 | F31: 2000 | G31: =E31+F31 -> 2869.5426 | H31: =B31-G31 -> 138962.89
A32: 31 | B32: =H31 -> 138962.89 | C32: =Simulador!C11 -> 1785.4006 | D32: =B32*Simulador!C7 -> 897.32844 | E32: =C32-D32 -> 888.0722 | F32: 2000 | G32: =E32+F32 -> 2888.0722 | H32: =B32-G32 -> 136074.82
A33: 32 | B33: =H32 -> 136074.82 | C33: =Simulador!C11 -> 1785.4006 | D33: =B33*Simulador!C7 -> 878.67923 | E33: =C33-D33 -> 906.72141 | F33: 2000 | G33: =E33+F33 -> 2906.7214 | H33: =B33-G33 -> 133168.1
A34: 33 | B34: =H33 -> 133168.1 | C34: =Simulador!C11 -> 1785.4006 | D34: =B34*Simulador!C7 -> 859.90958 | E34: =C34-D34 -> 925.49106 | F34: 2000 | G34: =E34+F34 -> 2925.4911 | H34: =B34-G34 -> 130242.61
A35: 34 | B35: =H34 -> 130242.61 | C35: =Simulador!C11 -> 1785.4006 | D35: =B35*Simulador!C7 -> 841.01874 | E35: =C35-D35 -> 944.3819 | F35: 2000 | G35: =E35+F35 -> 2944.3819 | H35: =B35-G35 -> 127298.22
A36: 35 | B36: =H35 -> 127298.22 | C36: =Simulador!C11 -> 1785.4006 | D36: =B36*Simulador!C7 -> 822.00591 | E36: =C36-D36 -> 963.39473 | F36: 2000 | G36: =E36+F36 -> 2963.3947 | H36: =B36-G36 -> 124334.83
A37: 36 | B37: =H36 -> 124334.83 | C37: =Simulador!C11 -> 1785.4006 | D37: =B37*Simulador!C7 -> 802.87031 | E37: =C37-D37 -> 982.53033 | F37: 2000 | G37: =E37+F37 -> 2982.5303 | H37: =B37-G37 -> 121352.3
A38: 37 | B38: =H37 -> 121352.3 | C38: =Simulador!C11 -> 1785.4006 | D38: =B38*Simulador!C7 -> 783.61114 | E38: =C38-D38 -> 1001.7895 | F38: 2000 | G38: =E38+F38 -> 3001.7895 | H38: =B38-G38 -> 118350.51
A39: 38 | B39: =H38 -> 118350.51 | C39: =Simulador!C11 -> 1785.4006 | D39: =B39*Simulador!C7 -> 764.22762 | E39: =C39-D39 -> 1021.173 | F39: 2000 | G39: =E39+F39 -> 3021.173 | H39: =B39-G39 -> 115329.34
A40: 39 | B40: =H39 -> 115329.34 | C40: =Simulador!C11 -> 1785.4006 | D40: =B40*Simulador!C7 -> 744.71892 | E40: =C40-D40 -> 1040.6817 | F40: 2000 | G40: =E40+F40 -> 3040.6817 | H40: =B40-G40 -> 112288.66
A41: 40 | B41: =H40 -> 112288.66 | C41: =Simulador!C11 -> 1785.4006 | D41: =B41*Simulador!C7 -> 725.08426 | E41: =C41-D41 -> 1060.3164 | F41: 2000 | G41: =E41+F41 -> 3060.3164 | H41: =B41-G41 -> 109228.34
A42: 41 | B42: =H41 -> 109228.34 | C42: =Simulador!C11 -> 1785.4006 | D42: =B42*Simulador!C7 -> 705.3228 | E42: =C42-D42 -> 1080.0778 | F42: 2000 | G42: =E42+F42 -> 3080.0778 | H42: =B42-G42 -> 106148.26
A43: 42 | B43: =H42 -> 106148.26 | C43: =Simulador!C11 -> 1785.4006 | D43: =B43*Simulador!C7 -> 685.43374 | E43: =C43-D43 -> 1099.9669 | F43: 2000 | G43: =E43+F43 -> 3099.9669 | H43: =B43-G43 -> 103048.29
A44: 43 | B44: =H43 -> 103048.29 | C44: =Simulador!C11 -> 1785.4006 | D44: =B44*Simulador!C7 -> 665.41625 | E44: =C44-D44 -> 1119.9844 | F44: 2000 | G44: =E44+F44 -> 3119.9844 | H44: =B44-G44 -> 99928.31
A45: 44 | B45: =H44 -> 99928.31 | C45: =Simulador!C11 -> 1785.4006 | D45: =B45*Simulador!C7 -> 645.2695 | E45: =C45-D45 -> 1140.1311 | F45: 2000 | G45: =E45+F45 -> 3140.1311 | H45: =B45-G45 -> 96788.179
A46: 45 | B46: =H45 -> 96788.179 | C46: =Simulador!C11 -> 1785.4006 | D46: =B46*Simulador!C7 -> 624.99265 | E46: =C46-D46 -> 1160.408 | F46: 2000 | G46: =E46+F46 -> 3160.408 | H46: =B46-G46 -> 93627.771
A47: 46 | B47: =H46 -> 93627.771 | C47: =Simulador!C11 -> 1785.4006 | D47: =B47*Simulador!C7 -> 604.58487 | E47: =C47-D47 -> 1180.8158 | F47: 2000 | G47: =E47+F47 -> 3180.8158 | H47: =B47-G47 -> 90446.955
A48: 47 | B48: =H47 -> 90446.955 | C48: =Simulador!C11 -> 1785.4006 | D48: =B48*Simulador!C7 -> 584.04531 | E48: =C48-D48 -> 1201.3553 | F48: 2000 | G48: =E48+F48 -> 3201.3553 | H48: =B48-G48 -> 87245.6
A49: 48 | B49: =H48 -> 87245.6 | C49: =Simulador!C11 -> 1785.4006 | D49: =B49*Simulador!C7 -> 563.37312 | E49: =C49-D49 -> 1222.0275 | F49: 2000 | G49: =E49+F49 -> 3222.0275 | H49: =B49-G49 -> 84023.572
A50: 49 | B50: =H49 -> 84023.572 | C50: =Simulador!C11 -> 1785.4006 | D50: =B50*Simulador!C7 -> 542.56745 | E50: =C50-D50 -> 1242.8332 | F50: 2000 | G50: =E50+F50 -> 3242.8332 | H50: =B50-G50 -> 80780.739
A51: 50 | B51: =H50 -> 80780.739 | C51: =Simulador!C11 -> 1785.4006 | D51: =B51*Simulador!C7 -> 521.62742 | E51: =C51-D51 -> 1263.7732 | F51: 2000 | G51: =E51+F51 -> 3263.7732 | H51: =B51-G51 -> 77516.966
A52: 51 | B52: =H51 -> 77516.966 | C52: =Simulador!C11 -> 1785.4006 | D52: =B52*Simulador!C7 -> 500.55218 | E52: =C52-D52 -> 1284.8485 | F52: 2000 | G52: =E52+F52 -> 3284.8485 | H52: =B52-G52 -> 74232.117
A53: 52 | B53: =H52 -> 74232.117 | C53: =Simulador!C11 -> 1785.4006 | D53: =B53*Simulador!C7 -> 479.34085 | E53: =C53-D53 -> 1306.0598 | F53: 2000 | G53: =E53+F53 -> 3306.0598 | H53: =B53-G53 -> 70926.058
A54: 53 | B54: =H53 -> 70926.058 | C54: =Simulador!C11 -> 1785.4006 | D54: =B54*Simulador!C7 -> 457.99255 | E54: =C54-D54 -> 1327.4081 | F54: 2000 | G54: =E54+F54 -> 3327.4081 | H54: =B54-G54 -> 67598.649
A55: 54 | B55: =H54 -> 67598.649 | C55: =Simulador!C11 -> 1785.4006 | D55: =B55*Simulador!C7 -> 436.5064 | E55: =C55-D55 -> 1348.8942 | F55: 2000 | G55: =E55+F55 -> 3348.8942 | H55: =B55-G55 -> 64249.755
A56: 55 | B56: =H55 -> 64249.755 | C56: =Simulador!C11 -> 1785.4006 | D56: =B56*Simulador!C7 -> 414.8815 | E56: =C56-D56 -> 1370.5191 | F56: 2000 | G56: =E56+F56 -> 3370.5191 | H56: =B56-G56 -> 60879.236
A57: 56 | B57: =H56 -> 60879.236 | C57: =Simulador!C11 -> 1785.4006 | D57: =B57*Simulador!C7 -> 393.11697 | E57: =C57-D57 -> 1392.2837 | F57: 2000 | G57: =E57+F57 -> 3392.2837 | H57: =B57-G57 -> 57486.952
A58: 57 | B58: =H57 -> 57486.952 | C58: =Simulador!C11 -> 1785.4006 | D58: =B58*Simulador!C7 -> 371.21189 | E58: =C58-D58 -> 1414.1887 | F58: 2000 | G58: =E58+F58 -> 3414.1887 | H58: =B58-G58 -> 54072.764
A59: 58 | B59: =H58 -> 54072.764 | C59: =Simulador!C11 -> 1785.4006 | D59: =B59*Simulador!C7 -> 349.16537 | E59: =C59-D59 -> 1436.2353 | F59: 2000 | G59: =E59+F59 -> 3436.2353 | H59: =B59-G59 -> 50636.528
A60: 59 | B60: =H59 -> 50636.528 | C60: =Simulador!C11 -> 1785.4006 | D60: =B60*Simulador!C7 -> 326.97648 | E60: =C60-D60 -> 1458.4242 | F60: 2000 | G60: =E60+F60 -> 3458.4242 | H60: =B60-G60 -> 47178.104
A61: 60 | B61: =H60 -> 47178.104 | C61: =Simulador!C11 -> 1785.4006 | D61: =B61*Simulador!C7 -> 304.64432 | E61: =C61-D61 -> 1480.7563 | F61: 2000 | G61: =E61+F61 -> 3480.7563 | H61: =B61-G61 -> 43697.348
A62: 61 | B62: =H61 -> 43697.348 | C62: =Simulador!C11 -> 1785.4006 | D62: =B62*Simulador!C7 -> 282.16794 | E62: =C62-D62 -> 1503.2327 | F62: 2000 | G62: =E62+F62 -> 3503.2327 | H62: =B62-G62 -> 40194.115
A63: 62 | B63: =H62 -> 40194.115 | C63: =Simulador!C11 -> 1785.4006 | D63: =B63*Simulador!C7 -> 259.54643 | E63: =C63-D63 -> 1525.8542 | F63: 2000 | G63: =E63+F63 -> 3525.8542 | H63: =B63-G63 -> 36668.261
A64: 63 | B64: =H63 -> 36668.261 | C64: =Simulador!C11 -> 1785.4006 | D64: =B64*Simulador!C7 -> 236.77885 | E64: =C64-D64 -> 1548.6218 | F64: 2000 | G64: =E64+F64 -> 3548.6218 | H64: =B64-G64 -> 33119.639
A65: 64 | B65: =H64 -> 33119.639 | C65: =Simulador!C11 -> 1785.4006 | D65: =B65*Simulador!C7 -> 213.86425 | E65: =C65-D65 -> 1571.5364 | F65: 2000 | G65: =E65+F65 -> 3571.5364 | H65: =B65-G65 -> 29548.103
A66: 65 | B66: =H65 -> 29548.103 | C66: =Simulador!C11 -> 1785.4006 | D66: =B66*Simulador!C7 -> 190.80168 | E66: =C66-D66 -> 1594.599 | F66: 2000 | G66: =E66+F66 -> 3594.599 | H66: =B66-G66 -> 25953.504
A67: 66 | B67: =H66 -> 25953.504 | C67: =Simulador!C11 -> 1785.4006 | D67: =B67*Simulador!C7 -> 167.59019 | E67: =C67-D67 -> 1617.8105 | F67: 2000 | G67: =E67+F67 -> 3617.8105 | H67: =B67-G67 -> 22335.693
A68: 67 | B68: =H67 -> 22335.693 | C68: =Simulador!C11 -> 1785.4006 | D68: =B68*Simulador!C7 -> 144.22881 | E68: =C68-D68 -> 1641.1718 | F68: 2000 | G68: =E68+F68 -> 3641.1718 | H68: =B68-G68 -> 18694.522
A69: 68 | B69: =H68 -> 18694.522 | C69: =Simulador!C11 -> 1785.4006 | D69: =B69*Simulador!C7 -> 120.71659 | E69: =C69-D69 -> 1664.6841 | F69: 2000 | G69: =E69+F69 -> 3664.6841 | H69: =B69-G69 -> 15029.837
A70: 69 | B70: =H69 -> 15029.837 | C70: =Simulador!C11 -> 1785.4006 | D70: =B70*Simulador!C7 -> 97.052534 | E70: =C70-D70 -> 1688.3481 | F70: 2000 | G70: =E70+F70 -> 3688.3481 | H70: =B70-G70 -> 11341.489
A71: 70 | B71: =H70 -> 11341.489 | C71: =Simulador!C11 -> 1785.4006 | D71: =B71*Simulador!C7 -> 73.235674 | E71: =C71-D71 -> 1712.165 | F71: 2000 | G71: =E71+F71 -> 3712.165 | H71: =B71-G71 -> 7629.3244
A72: 71 | B72: =H71 -> 7629.3244 | C72: =Simulador!C11 -> 1785.4006 | D72: =B72*Simulador!C7 -> 49.265021 | E72: =C72-D72 -> 1736.1356 | F72: 2000 | G72: =E72+F72 -> 3736.1356 | H72: =B72-G72 -> 3893.1888
A73: 72 | B73: =H72 -> 3893.1888 | C73: =Simulador!C11 -> 1785.4006 | D73: =B73*Simulador!C7 -> 25.139582 | E73: =C73-D73 -> 1760.2611 | F73: 2000 | G73: =E73+F73 -> 3760.2611 | H73: =B73-G73 -> 132.92772
A74: 73 | B74: =H73 -> 132.92772 | C74: =Simulador!C11 -> 1785.4006 | D74: =B74*Simulador!C7 -> 0.85835739 | E74: =C74-D74 -> 1784.5423 | F74: 2000 | G74: =E74+F74 -> 3784.5423 | H74: =B74-G74 -> -3651.6146
A75: 74 | B75: =H74 -> -3651.6146 | C75: =Simulador!C11 -> 1785.4006 | D75: =B75*Simulador!C7 -> -23.579659 | E75: =C75-D75 -> 1808.9803 | F75: 2000 | G75: =E75+F75 -> 3808.9803 | H75: =B75-G75 -> -7460.5949
A76: 75 | B76: =H75 -> -7460.5949 | C76: =Simulador!C11 -> 1785.4006 | D76: =B76*Simulador!C7 -> -48.17548 | E76: =C76-D76 -> 1833.5761 | F76: 2000 | G76: =E76+F76 -> 3833.5761 | H76: =B76-G76 -> -11294.171
A77: 76 | B77: =H76 -> -11294.171 | C77: =Simulador!C11 -> 1785.4006 | D77: =B77*Simulador!C7 -> -72.930124 | E77: =C77-D77 -> 1858.3308 | F77: 2000 | G77: =E77+F77 -> 3858.3308 | H77: =B77-G77 -> -15152.502
A78: 77 | B78: =H77 -> -15152.502 | C78: =Simulador!C11 -> 1785.4006 | D78: =B78*Simulador!C7 -> -97.844617 | E78: =C78-D78 -> 1883.2453 | F78: 2000 | G78: =E78+F78 -> 3883.2453 | H78: =B78-G78 -> -19035.747
A79: 78 | B79: =H78 -> -19035.747 | C79: =Simulador!C11 -> 1785.4006 | D79: =B79*Simulador!C7 -> -122.91999 | E79: =C79-D79 -> 1908.3206 | F79: 2000 | G79: =E79+F79 -> 3908.3206 | H79: =B79-G79 -> -22944.068
A80: 79 | B80: =H79 -> -22944.068 | C80: =Simulador!C11 -> 1785.4006 | D80: =B80*Simulador!C7 -> -148.15728 | E80: =C80-D80 -> 1933.5579 | F80: 2000 | G80: =E80+F80 -> 3933.5579 | H80: =B80-G80 -> -26877.626
A81: 80 | B81: =H80 -> -26877.626 | C81: =Simulador!C11 -> 1785.4006 | D81: =B81*Simulador!C7 -> -173.55754 | E81: =C81-D81 -> 1958.9582 | F81: 0 | G81: =E81+F81 -> 1958.9582 | H81: =B81-G81 -> -28836.584
A82: 81 | B82: =H81 -> -28836.584 | C82: =Simulador!C11 -> 1785.4006 | D82: =B82*Simulador!C7 -> -186.20717 | E82: =C82-D82 -> 1971.6078 | F82: 0 | G82: =E82+F82 -> 1971.6078 | H82: =B82-G82 -> -30808.192
A83: 82 | B83: =H82 -> -30808.192 | C83: =Simulador!C11 -> 1785.4006 | D83: =B83*Simulador!C7 -> -198.93848 | E83: =C83-D83 -> 1984.3391 | F83: 0 | G83: =E83+F83 -> 1984.3391 | H83: =B83-G83 -> -32792.531
A84: 83 | B84: =H83 -> -32792.531 | C84: =Simulador!C11 -> 1785.4006 | D84: =B84*Simulador!C7 -> -211.752 | E84: =C84-D84 -> 1997.1526 | F84: 0 | G84: =E84+F84 -> 1997.1526 | H84: =B84-G84 -> -34789.683
A85: 84 | B85: =H84 -> -34789.683 | C85: =Simulador!C11 -> 1785.4006 | D85: =B85*Simulador!C7 -> -224.64826 | E85: =C85-D85 -> 2010.0489 | F85: 0 | G85: =E85+F85 -> 2010.0489 | H85: =B85-G85 -> -36799.732
A86: 85 | B86: =H85 -> -36799.732 | C86: =Simulador!C11 -> 1785.4006 | D86: =B86*Simulador!C7 -> -237.6278 | E86: =C86-D86 -> 2023.0284 | F86: 0 | G86: =E86+F86 -> 2023.0284 | H86: =B86-G86 -> -38822.761
A87: 86 | B87: =H86 -> -38822.761 | C87: =Simulador!C11 -> 1785.4006 | D87: =B87*Simulador!C7 -> -250.69115 | E87: =C87-D87 -> 2036.0918 | F87: 0 | G87: =E87+F87 -> 2036.0918 | H87: =B87-G87 -> -40858.852
A88: 87 | B88: =H87 -> -40858.852 | C88: =Simulador!C11 -> 1785.4006 | D88: =B88*Simulador!C7 -> -263.83886 | E88: =C88-D88 -> 2049.2395 | F88: 0 | G88: =E88+F88 -> 2049.2395 | H88: =B88-G88 -> -42908.092
A89: 88 | B89: =H88 -> -42908.092 | C89: =Simulador!C11 -> 1785.4006 | D89: =B89*Simulador!C7 -> -277.07146 | E89: =C89-D89 -> 2062.4721 | F89: 0 | G89: =E89+F89 -> 2062.4721 | H89: =B89-G89 -> -44970.564
A90: 89 | B90: =H89 -> -44970.564 | C90: =Simulador!C11 -> 1785.4006 | D90: =B90*Simulador!C7 -> -290.38951 | E90: =C90-D90 -> 2075.7902 | F90: 0 | G90: =E90+F90 -> 2075.7902 | H90: =B90-G90 -> -47046.354
A91: 90 | B91: =H90 -> -47046.354 | C91: =Simulador!C11 -> 1785.4006 | D91: =B91*Simulador!C7 -> -303.79356 | E91: =C91-D91 -> 2089.1942 | F91: 0 | G91: =E91+F91 -> 2089.1942 | H91: =B91-G91 -> -49135.548
A92: 91 | B92: =H91 -> -49135.548 | C92: =Simulador!C11 -> 1785.4006 | D92: =B92*Simulador!C7 -> -317.28417 | E92: =C92-D92 -> 2102.6848 | F92: 0 | G92: =E92+F92 -> 2102.6848 | H92: =B92-G92 -> -51238.233
A93: 92 | B93: =H92 -> -51238.233 | C93: =Simulador!C11 -> 1785.4006 | D93: =B93*Simulador!C7 -> -330.86188 | E93: =C93-D93 -> 2116.2625 | F93: 0 | G93: =E93+F93 -> 2116.2625 | H93: =B93-G93 -> -53354.496
A94: 93 | B94: =H93 -> -53354.496 | C94: =Simulador!C11 -> 1785.4006 | D94: =B94*Simulador!C7 -> -344.52728 | E94: =C94-D94 -> 2129.9279 | F94: 0 | G94: =E94+F94 -> 2129.9279 | H94: =B94-G94 -> -55484.424
A95: 94 | B95: =H94 -> -55484.424 | C95: =Simulador!C11 -> 1785.4006 | D95: =B95*Simulador!C7 -> -358.28091 | E95: =C95-D95 -> 2143.6816 | F95: 0 | G95: =E95+F95 -> 2143.6816 | H95: =B95-G95 -> -57628.105
A96: 95 | B96: =H95 -> -57628.105 | C96: =Simulador!C11 -> 1785.4006 | D96: =B96*Simulador!C7 -> -372.12336 | E96: =C96-D96 -> 2157.524 | F96: 0 | G96: =E96+F96 -> 2157.524 | H96: =B96-G96 -> -59785.629
A97: 96 | B97: =H96 -> -59785.629 | C97: =Simulador!C11 -> 1785.4006 | D97: =B97*Simulador!C7 -> -386.05519 | E97: =C97-D97 -> 2171.4558 | F97: 0 | G97: =E97+F97 -> 2171.4558 | H97: =B97-G97 -> -61957.085
A98: 97 | B98: =H97 -> -61957.085 | C98: =Simulador!C11 -> 1785.4006 | D98: =B98*Simulador!C7 -> -400.07699 | E98: =C98-D98 -> 2185.4776 | F98: 0 | G98: =E98+F98 -> 2185.4776 | H98: =B98-G98 -> -64142.563
A99: 98 | B99: =H98 -> -64142.563 | C99: =Simulador!C11 -> 1785.4006 | D99: =B99*Simulador!C7 -> -414.18932 | E99: =C99-D99 -> 2199.59 | F99: 0 | G99: =E99+F99 -> 2199.59 | H99: =B99-G99 -> -66342.153
A100: 99 | B100: =H99 -> -66342.153 | C100: =Simulador!C11 -> 1785.4006 | D100: =B100*Simulador!C7 -> -428.39279 | E100: =C100-D100 -> 2213.7934 | F100: 0 | G100: =E100+F100 -> 2213.7934 | H100: =B100-G100 -> -68555.946
...

Sheet Resultados
A1: Plazo Original (meses) | B1: =Simulador!C8 -> 240
A2: Mes de Cancelacion | B2: {=MATCH(TRUE,Amortizacion!H:H<=0,0)-1} -> 73
A3: Meses Reducidos | B3: =B1-B2 -> 167
A5: Simulacion pago rapido
A6: Años | B6: Cuota Necesaria
A7: 3 | B7: =PMT(Simulador!C7,3*12,-Simulador!C5) -> 6790.4819
A8: 4 | B8: =PMT(Simulador!C7,4*12,-Simulador!C5) -> 5284.2006
A9: 6 | B9: =PMT(Simulador!C7,6*12,-Simulador!C5) -> 3786.8567
